README.txt
setup.py
StressModellingPackageTest/__init__.py
StressModellingPackageTest/setup.py
StressModellingPackageTest.egg-info/PKG-INFO
StressModellingPackageTest.egg-info/SOURCES.txt
StressModellingPackageTest.egg-info/dependency_links.txt
StressModellingPackageTest.egg-info/top_level.txt
StressModellingPackageTest/data/Adjacent list ac zones_test.xlsx
StressModellingPackageTest/data/SDG_Adjacency.xlsx
StressModellingPackageTest/data/States_Neighbors2020_updated.xlsx
StressModellingPackageTest/data/PreComputedGraphs/Adjacent list ac zones.xlsx
StressModellingPackageTest/data/PreComputedGraphs/States_Neighbors.xlsx
StressModellingPackageTest/data/PreComputedGraphs/TalukAdjacencyFrame.xlsx