Metadata-Version: 1.1
Name: StressModellingPackageTest
Version: 0.0.57
Summary:  
Home-page: UNKNOWN
Author: Sowmith Nandan
Author-email: sowmith.nandan@iiit.ac.in
License: MIT
Keywords: Stress Modelling
Platform: UNKNOWN
Classifier: Development Status :: 5 - Production/Stable
Classifier: Intended Audience :: Education
Classifier: Operating System :: Microsoft :: Windows :: Windows 10
Classifier: License :: OSI Approved :: MIT License
Classifier: Programming Language :: Python :: 3
